werkudara/__main__.py
werkudara/api.py
werkudara/export_pyuic5.sh
werkudara/thread.py
werkudara/ui/about.ui
werkudara/ui/changelog.ui
werkudara/ui/help.ui
werkudara/ui/license.ui
werkudara/ui/main_gui.ui
werkudara/ui/universal_dialog.ui
werkudara/ui_exported/__init__.py
werkudara/ui_exported/about.py
werkudara/ui_exported/changelog.py
werkudara/ui_exported/help.py
werkudara/ui_exported/license.py
werkudara/ui_exported/main_gui.py
werkudara/ui_exported/universal_dialog.py
werkudara-1.2.0.dist-info/METADATA
werkudara-1.2.0.dist-info/WHEEL
werkudara-1.2.0.dist-info/licenses/LICENSE
werkudara-1.2.0.dist-info/RECORD
