Metadata-Version: 2.3
Name: werkudara
Version: 1.2.0
Summary: Automatically synchronize author and lecturer data in https://bima.kemdikbud.go.id
Project-URL: Homepage, https://github.com/groaking/werkudara
Project-URL: Repository, https://github.com/groaking/werkudara.git
Project-URL: Changelog, https://github.com/groaking/werkudara/blob/master/CHANGELOG.md
Project-URL: Issues, https://github.com/groaking/werkudara/issues
Author-email: Samarthya Lykamanuella <lykamanuella@outlook.com>
Maintainer-email: Samarthya Lykamanuella <lykamanuella@outlook.com>
License: GNU General Public License v3.0 or later
License-File: LICENSE
Keywords: BIMA,Dikti,Diktiristek,Kemdikbud,Kemendikbud,Kemenristekdikti,Ristek,Ristekdikti,administrator,autosync,control panel,sync
Classifier: Development Status :: 3 - Alpha
Classifier: Environment :: X11 Applications :: Qt
Classifier: Intended Audience :: Science/Research
Classifier: Intended Audience :: System Administrators
Classifier: License :: OSI Approved :: GNU General Public License v3 (GPLv3)
Classifier: Natural Language :: English
Classifier: Natural Language :: Indonesian
Classifier: Operating System :: OS Independent
Classifier: Programming Language :: Python :: 3
Classifier: Topic :: Database
Classifier: Topic :: System :: Systems Administration
Classifier: Topic :: Utilities
Requires-Python: >=3.9
Requires-Dist: lxml
Requires-Dist: openpyxl
Requires-Dist: platformdirs
Requires-Dist: pyqt5
Requires-Dist: requests
